{
  "id": "MAP_SPA_FRONT",
  "name": "SpaFront",
  "layout": "LAYOUT_SPA_FRONT",
  "music": "MUS_ABANDONED_SHIP",
  "region_map_section": "MAPSEC_ABANDONED_SHIP",
  "requires_flash": false,
  "weather": "WEATHER_NONE",
  "map_type": "MAP_TYPE_NONE",
  "allow_cycling": false,
  "allow_escaping": false,
  "allow_running": true,
  "show_map_name": false,
  "battle_scene": "MAP_BATTLE_SCENE_NORMAL",
  "connections": null,
  "object_events": [
    {
      "graphics_id": "OBJ_EVENT_GFX_TRUCK",
      "x": 22,
      "y": 44,
      "elevation": 0,
      "movement_type": "MOVEMENT_TYPE_NONE",
      "movement_range_x": 0,
      "movement_range_y": 0,
      "trainer_type": "TRAINER_TYPE_NONE",
      "trainer_sight_or_berry_tree_id": "0",
      "script": "NULL",
      "flag": "FLAG_HIDE_TRUCK"
    }
  ],
  "warp_events": [
    {
      "x": 13,
      "y": 43,
      "elevation": 0,
      "dest_map": "MAP_SPA_FRONT",
      "dest_warp_id": "0"
    },
    {
      "x": 14,
      "y": 7,
      "elevation": 0,
      "dest_map": "MAP_SPA_INTERIOR",
      "dest_warp_id": "0"
    }
  ],
  "coord_events": [
    {
      "type": "trigger",
      "x": 18,
      "y": 39,
      "elevation": 0,
      "var": "VAR_TEMP_0",
      "var_value": "0",
      "script": "SpaFront_EventScript_RoadRight"
    },
    {
      "type": "trigger",
      "x": 18,
      "y": 40,
      "elevation": 0,
      "var": "VAR_TEMP_0",
      "var_value": "0",
      "script": "SpaFront_EventScript_RoadRight"
    },
    {
      "type": "trigger",
      "x": 18,
      "y": 41,
      "elevation": 0,
      "var": "VAR_TEMP_0",
      "var_value": "0",
      "script": "SpaFront_EventScript_RoadRight"
    },
    {
      "type": "trigger",
      "x": 18,
      "y": 42,
      "elevation": 0,
      "var": "VAR_TEMP_0",
      "var_value": "0",
      "script": "SpaFront_EventScript_RoadRight"
    },
    {
      "type": "trigger",
      "x": 18,
      "y": 43,
      "elevation": 0,
      "var": "VAR_TEMP_0",
      "var_value": "0",
      "script": "SpaFront_EventScript_RoadRight"
    },
    {
      "type": "trigger",
      "x": 18,
      "y": 44,
      "elevation": 0,
      "var": "VAR_TEMP_0",
      "var_value": "0",
      "script": "SpaFront_EventScript_RoadRight"
    },
    {
      "type": "trigger",
      "x": 18,
      "y": 45,
      "elevation": 0,
      "var": "VAR_TEMP_0",
      "var_value": "0",
      "script": "SpaFront_EventScript_RoadRight"
    },
    {
      "type": "trigger",
      "x": 18,
      "y": 46,
      "elevation": 0,
      "var": "VAR_TEMP_0",
      "var_value": "0",
      "script": "SpaFront_EventScript_RoadRight"
    },
    {
      "type": "trigger",
      "x": 18,
      "y": 47,
      "elevation": 0,
      "var": "VAR_TEMP_0",
      "var_value": "0",
      "script": "SpaFront_EventScript_RoadRight"
    },
    {
      "type": "trigger",
      "x": 7,
      "y": 38,
      "elevation": 0,
      "var": "VAR_TEMP_0",
      "var_value": "0",
      "script": "SpaFront_EventScript_RoadLeft"
    },
    {
      "type": "trigger",
      "x": 7,
      "y": 39,
      "elevation": 0,
      "var": "VAR_TEMP_0",
      "var_value": "0",
      "script": "SpaFront_EventScript_RoadLeft"
    },
    {
      "type": "trigger",
      "x": 7,
      "y": 40,
      "elevation": 0,
      "var": "VAR_TEMP_0",
      "var_value": "0",
      "script": "SpaFront_EventScript_RoadLeft"
    },
    {
      "type": "trigger",
      "x": 7,
      "y": 41,
      "elevation": 0,
      "var": "VAR_TEMP_0",
      "var_value": "0",
      "script": "SpaFront_EventScript_RoadLeft"
    },
    {
      "type": "trigger",
      "x": 7,
      "y": 42,
      "elevation": 0,
      "var": "VAR_TEMP_0",
      "var_value": "0",
      "script": "SpaFront_EventScript_RoadLeft"
    },
    {
      "type": "trigger",
      "x": 7,
      "y": 43,
      "elevation": 0,
      "var": "VAR_TEMP_0",
      "var_value": "0",
      "script": "SpaFront_EventScript_RoadLeft"
    },
    {
      "type": "trigger",
      "x": 7,
      "y": 44,
      "elevation": 0,
      "var": "VAR_TEMP_0",
      "var_value": "0",
      "script": "SpaFront_EventScript_RoadLeft"
    },
    {
      "type": "trigger",
      "x": 7,
      "y": 45,
      "elevation": 0,
      "var": "VAR_TEMP_0",
      "var_value": "0",
      "script": "SpaFront_EventScript_RoadLeft"
    },
    {
      "type": "trigger",
      "x": 7,
      "y": 46,
      "elevation": 0,
      "var": "VAR_TEMP_0",
      "var_value": "0",
      "script": "SpaFront_EventScript_RoadLeft"
    },
    {
      "type": "trigger",
      "x": 7,
      "y": 47,
      "elevation": 0,
      "var": "VAR_TEMP_0",
      "var_value": "0",
      "script": "SpaFront_EventScript_RoadLeft"
    }
  ],
  "bg_events": [
    {
      "type": "sign",
      "x": 17,
      "y": 40,
      "elevation": 0,
      "player_facing_dir": "BG_EVENT_PLAYER_FACING_NORTH",
      "script": "SpaFront_EventScript_Sign"
    }
  ]
}
